{
    "Movies": [
        {
            "filename": "12 Angry Men.mp4",
            "size": 734077147
        },
        {
            "filename": "12 Angry Men.srt",
            "size": 146365
        },
        {
            "filename": "127 Hours.mp4",
            "size": 682735600
        },
        {
            "filename": "127 Hours.srt",
            "size": 36487
        },
        {
            "filename": "Cover.jpg",
            "size": 125577
        },
        {
            "filename": "2012.mkv",
            "size": 1162277992
        },
        {
            "filename": "2012.srt",
            "size": 134017
        },
        {
            "filename": "Cover.jpg",
            "size": 373761
        },
        {
            "filename": "A Better Life.mkv",
            "size": 955807280
        },
        {
            "filename": "A Better Life.srt",
            "size": 60911
        },
        {
            "filename": "A Man Called Ove.mp4",
            "size": 892267553
        },
        {
            "filename": "A Man Called Ove.srt",
            "size": 87512
        },
        {
            "filename": "A Silent Voice.mp4",
            "size": 1176592222
        },
        {
            "filename": "A Silent Voice.srt",
            "size": 121887
        },
        {
            "filename": "About Time.mp4",
            "size": 912049358
        },
        {
            "filename": "About Time.srt",
            "size": 128116
        },
        {
            "filename": "Cover.jpg",
            "size": 107140
        },
        {
            "filename": "Alien.mp4",
            "size": 733632010
        },
        {
            "filename": "Alien.srt",
            "size": 77213
        },
        {
            "filename": "Aliens.mp4",
            "size": 938576175
        },
        {
            "filename": "Aliens.srt",
            "size": 121119
        },
        {
            "filename": "American Sniper.mp4",
            "size": 920075743
        },
        {
            "filename": "American Sniper.srt",
            "size": 141576
        },
        {
            "filename": "Andaz Apna Apna.mp4",
            "size": 1222843269
        },
        {
            "filename": "Angels & Demons.mp4",
            "size": 838762527
        },
        {
            "filename": "Cover.jpg",
            "size": 165271
        },
        {
            "filename": "Argo.mp4",
            "size": 787755488
        },
        {
            "filename": "Argo.srt",
            "size": 102607
        },
        {
            "filename": "Cover.jpg",
            "size": 81231
        },
        {
            "filename": "Babam ve Oglum.mp4",
            "size": 989170475
        },
        {
            "filename": "Back to the Future.mp4",
            "size": 733639131
        },
        {
            "filename": "Back to the Future.srt",
            "size": 125647
        },
        {
            "filename": "Batman V Superman Dawn Of Justice.mp4",
            "size": 1424899467
        },
        {
            "filename": "Batman V Superman Dawn Of Justice.srt",
            "size": 142238
        },
        {
            "filename": "Before Sunrise.mp4",
            "size": 920721071
        },
        {
            "filename": "Before Sunrise.srt",
            "size": 118570
        },
        {
            "filename": "Begin Again.mp4",
            "size": 848159860
        },
        {
            "filename": "Begin Again.srt",
            "size": 104370
        },
        {
            "filename": "Better Days.mp4",
            "size": 2685498411
        },
        {
            "filename": "Better Days.srt",
            "size": 86484
        },
        {
            "filename": "Birdman.mp4",
            "size": 908665370
        },
        {
            "filename": "Birdman.srt",
            "size": 143220
        },
        {
            "filename": "._Blade.Runner.2049.2017.1080p.BluRay.x264-[YTS.AG].mp4",
            "size": 4096
        },
        {
            "filename": "Blade Runner 2049.mp4",
            "size": 2693638088
        },
        {
            "filename": "Blade Runner 2049.srt",
            "size": 73821
        },
        {
            "filename": "Cover.jpg",
            "size": 104107
        },
        {
            "filename": "Bombshell.mp4",
            "size": 1046491424
        },
        {
            "filename": "Bombshell.srt",
            "size": 153830
        },
        {
            "filename": "Borg vs. McEnroe.mp4",
            "size": 835420663
        },
        {
            "filename": "Borg vs. McEnroe.srt",
            "size": 52250
        },
        {
            "filename": "Boyhood.mp4",
            "size": 1047131753
        },
        {
            "filename": "Boyhood.srt",
            "size": 243196
        },
        {
            "filename": "Cover.jpg",
            "size": 137662
        },
        {
            "filename": "Braveheart.mp4",
            "size": 1180415380
        },
        {
            "filename": "Braveheart.srt",
            "size": 87521
        },
        {
            "filename": "Bridge of Spies.mp4",
            "size": 1083900711
        },
        {
            "filename": "Bridge of Spies.srt",
            "size": 152267
        },
        {
            "filename": "Brothers.mp4",
            "size": 734477611
        },
        {
            "filename": "Brothers.srt",
            "size": 68656
        },
        {
            "filename": "Bruce Almighty.mp4",
            "size": 805269521
        },
        {
            "filename": "Bruce Almighty.srt",
            "size": 111291
        },
        {
            "filename": "Burnt.mp4",
            "size": 794245608
        },
        {
            "filename": "Burnt.srt",
            "size": 88472
        },
        {
            "filename": "Cache.mkv",
            "size": 1106965360
        },
        {
            "filename": "Captain Phillips.mkv",
            "size": 943779376
        },
        {
            "filename": "Captain Phillips.srt",
            "size": 110175
        },
        {
            "filename": "Cars.mp4",
            "size": 1906497402
        },
        {
            "filename": "Cars.srt",
            "size": 119384
        },
        {
            "filename": "Cast Away.mp4",
            "size": 996573075
        },
        {
            "filename": "Cast Away.srt",
            "size": 55948
        },
        {
            "filename": "Catch Me If You Can.mp4",
            "size": 1030042026
        },
        {
            "filename": "Catch Me If You Can.srt",
            "size": 170168
        },
        {
            "filename": "Children of Men.mkv",
            "size": 795628119
        },
        {
            "filename": "Cinderella Man.mkv",
            "size": 628422594
        },
        {
            "filename": "Civil War.mkv",
            "size": 2059860091
        },
        {
            "filename": "Coherence.mp4",
            "size": 736971863
        },
        {
            "filename": "Coherence.srt",
            "size": 131080
        },
        {
            "filename": "Confession of Murder.mkv",
            "size": 838697446
        },
        {
            "filename": "Confession of Murder.srt",
            "size": 91339
        },
        {
            "filename": "Cover.jpg",
            "size": 298989
        },
        {
            "filename": "Crash.mp4",
            "size": 905713826
        },
        {
            "filename": "Crash.srt",
            "size": 98133
        },
        {
            "filename": "Cover.jpg",
            "size": 227535
        },
        {
            "filename": "Creed.mp4",
            "size": 1024873327
        },
        {
            "filename": "Creed.srt",
            "size": 155675
        },
        {
            "filename": "Creed II.mp4",
            "size": 1170449423
        },
        {
            "filename": "Cover.jpg",
            "size": 289351
        },
        {
            "filename": "Dallas Buyers Club.mkv",
            "size": 890291625
        },
        {
            "filename": "Dawn of the Planet of the Apes.mp4",
            "size": 917319522
        },
        {
            "filename": "Dawn of the Planet of the Apes.srt",
            "size": 55690
        },
        {
            "filename": "Deadpool.mp4",
            "size": 850510804
        },
        {
            "filename": "Deadpool.srt",
            "size": 109319
        },
        {
            "filename": "Deadpool 2.mkv",
            "size": 1345366456
        },
        {
            "filename": "Departures.mp4",
            "size": 1213315002
        },
        {
            "filename": "Dhol.mkv",
            "size": 4723216777
        },
        {
            "filename": "Drishyam.mkv",
            "size": 993153321
        },
        {
            "filename": "Drive.mp4",
            "size": 742129213
        },
        {
            "filename": "Drive.srt",
            "size": 55382
        },
        {
            "filename": "._Dunkirk.2017.1080p.BluRay.x264-[YTS.AG].mp4",
            "size": 4096
        },
        {
            "filename": "Cover.jpg",
            "size": 462270
        },
        {
            "filename": "Dunkirk.mp4",
            "size": 1768550228
        },
        {
            "filename": "Dunkirk.srt",
            "size": 45652
        },
        {
            "filename": "Cover.jpg",
            "size": 432094
        },
        {
            "filename": "Edge of Tomorrow.mp4",
            "size": 854390520
        },
        {
            "filename": "Edge of Tomorrow.srt",
            "size": 102385
        },
        {
            "filename": "Elf.mp4",
            "size": 631066165
        },
        {
            "filename": "Elite Squad.mp4",
            "size": 842016848
        },
        {
            "filename": "Elite Squad.srt",
            "size": 117218
        },
        {
            "filename": "Enemy.mp4",
            "size": 739082350
        },
        {
            "filename": "Enemy.srt",
            "size": 32333
        },
        {
            "filename": "Cover.jpg",
            "size": 399906
        },
        {
            "filename": "Epic.mkv",
            "size": 943781209
        },
        {
            "filename": "Epic.srt",
            "size": 96376
        },
        {
            "filename": "Equals.mp4",
            "size": 780447513
        },
        {
            "filename": "Eternal Sunshine of the Spotless Mind.mp4",
            "size": 732790814
        },
        {
            "filename": "Eternal Sunshine of the Spotless Mind.srt",
            "size": 117662
        },
        {
            "filename": "Ex Machina.mp4",
            "size": 847344617
        },
        {
            "filename": "Ex Machina.srt",
            "size": 84667
        },
        {
            "filename": "Exodus- Gods and Kings.mkv",
            "size": 1176744994
        },
        {
            "filename": "Cover.jpg",
            "size": 187941
        },
        {
            "filename": "Extremely Loud & Incredibly Close.mkv",
            "size": 1060542794
        },
        {
            "filename": "Fantastic Beasts And Where To Find Them.mp4",
            "size": 1036204920
        },
        {
            "filename": "Fantastic Beasts And Where To Find Them.srt",
            "size": 90318
        },
        {
            "filename": "Fantastic Beasts- The Crimes Of Grindelwald.mp4",
            "size": 1198385639
        },
        {
            "filename": "Fantastic Beasts- The Crimes Of Grindelwald.srt",
            "size": 88704
        },
        {
            "filename": "Fast & Furious.mkv",
            "size": 670257515
        },
        {
            "filename": "Fast & Furious.srt",
            "size": 137558
        },
        {
            "filename": "Fast & Furious 6.mkv",
            "size": 1091126447
        },
        {
            "filename": "Fast & Furious 6.srt",
            "size": 90012
        },
        {
            "filename": "Fast Five.mkv",
            "size": 804450025
        },
        {
            "filename": "Fight Club.mkv",
            "size": 733667078
        },
        {
            "filename": "Fight Club.srt",
            "size": 146144
        },
        {
            "filename": "Fighting with My Family.mp4",
            "size": 964548802
        },
        {
            "filename": "Fighting with My Family.srt",
            "size": 136512
        },
        {
            "filename": "First Man.mp4",
            "size": 1252010935
        },
        {
            "filename": "Cover.jpg",
            "size": 93309
        },
        {
            "filename": "Following.mp4",
            "size": 629804155
        },
        {
            "filename": "Following.srt",
            "size": 64757
        },
        {
            "filename": "Friends with Benefits.mp4",
            "size": 733494352
        },
        {
            "filename": "Friends with Benefits.srt",
            "size": 151338
        },
        {
            "filename": "Cover.jpg",
            "size": 519500
        },
        {
            "filename": "Frozen.mp4",
            "size": 844474569
        },
        {
            "filename": "Frozen.srt",
            "size": 152101
        },
        {
            "filename": "Frozen II.mp4",
            "size": 993902451
        },
        {
            "filename": "Furious 7.mkv",
            "size": 1291824458
        },
        {
            "filename": "Cover.jpg",
            "size": 392567
        },
        {
            "filename": "Godzilla Vs. Kong.mp4",
            "size": 2238991883
        },
        {
            "filename": "Godzilla Vs. Kong.srt",
            "size": 62290
        },
        {
            "filename": "Gone Baby Gone.mp4",
            "size": 787081522
        },
        {
            "filename": "Gone Baby Gone.srt",
            "size": 128812
        },
        {
            "filename": "Good Will Hunting.mp4",
            "size": 892110577
        },
        {
            "filename": "Good Will Hunting.srt",
            "size": 154659
        },
        {
            "filename": "Cover.jpg",
            "size": 225630
        },
        {
            "filename": "Gravity.mp4",
            "size": 739104069
        },
        {
            "filename": "Gravity.srt",
            "size": 58713
        },
        {
            "filename": "Groundhog Day.mp4",
            "size": 682994720
        },
        {
            "filename": "Groundhog Day.srt",
            "size": 94739
        },
        {
            "filename": "Hacksaw Ridge.mp4",
            "size": 1078589921
        },
        {
            "filename": "Hacksaw Ridge.srt",
            "size": 101099
        },
        {
            "filename": "Harry Potter and the Chamber of Secrets.mkv",
            "size": 628979934
        },
        {
            "filename": "Harry Potter and the Chamber of Secrets.srt",
            "size": 118187
        },
        {
            "filename": "Harry Potter And The Deathly Hallows Part 2.mp4",
            "size": 1078263935
        },
        {
            "filename": "Harry Potter And The Deathly Hallows Part 2.srt",
            "size": 72926
        },
        {
            "filename": "Harry Potter and the Deathly Hallows Part I.mp4",
            "size": 2152024532
        },
        {
            "filename": "Harry Potter and the Deathly Hallows Part I.srt",
            "size": 96702
        },
        {
            "filename": "Harry Potter and the Goblet of Fire.mkv",
            "size": 628077865
        },
        {
            "filename": "Harry Potter and the Goblet of Fire.srt",
            "size": 129555
        },
        {
            "filename": "Harry Potter and the Half Blood Prince.mkv",
            "size": 682790506
        },
        {
            "filename": "Harry Potter and the Half Blood Prince.srt",
            "size": 109745
        },
        {
            "filename": "Harry Potter and the Order of the Phoenix.mkv",
            "size": 576581164
        },
        {
            "filename": "Harry Potter and the Order of the Phoenix.srt",
            "size": 100099
        },
        {
            "filename": "Harry Potter and the Prisoner of Azkaban.mkv",
            "size": 576131414
        },
        {
            "filename": "Harry Potter and the Prisoner of Azkaban.srt",
            "size": 122118
        },
        {
            "filename": "Heat.mkv",
            "size": 891223780
        },
        {
            "filename": "Her.mp4",
            "size": 1991522644
        },
        {
            "filename": "Her.srt",
            "size": 132903
        },
        {
            "filename": "Honey Boy.mp4",
            "size": 911277586
        },
        {
            "filename": "Honey Boy.srt",
            "size": 90730
        },
        {
            "filename": "Hotel Mumbai.mp4",
            "size": 1102547535
        },
        {
            "filename": "How to Train Your Dragon.mkv",
            "size": 723960276
        },
        {
            "filename": "How to Train Your Dragon.srt",
            "size": 64356
        },
        {
            "filename": "Hulchul.mkv",
            "size": 1284752807
        },
        {
            "filename": "I Lost My Body.mp4",
            "size": 776887140
        },
        {
            "filename": "I Lost My Body.srt",
            "size": 31101
        },
        {
            "filename": "I Saw the Devil.mp4",
            "size": 1463943412
        },
        {
            "filename": "I Saw the Devil.srt",
            "size": 46414
        },
        {
            "filename": "I, Daniel Blake.mp4",
            "size": 761619656
        },
        {
            "filename": "I, Daniel Blake.srt",
            "size": 128086
        },
        {
            "filename": "In Bruges.mp4",
            "size": 683419281
        },
        {
            "filename": "In Bruges.srt",
            "size": 89701
        },
        {
            "filename": "Incendies.mp4",
            "size": 1154975451
        },
        {
            "filename": "Incendies.srt",
            "size": 53160
        },
        {
            "filename": "Incredibles 2.mp4",
            "size": 1044228698
        },
        {
            "filename": "Incredibles 2.srt",
            "size": 185536
        },
        {
            "filename": "Inferno.mp4",
            "size": 956158068
        },
        {
            "filename": "Inglourious  Basterads.mp4",
            "size": 977025702
        },
        {
            "filename": "Inglourious  Basterads.srt",
            "size": 137244
        },
        {
            "filename": "Cover.jpg",
            "size": 86978
        },
        {
            "filename": "Insomnia.mp4",
            "size": 490142220
        },
        {
            "filename": "Insomnia.srt",
            "size": 88708
        },
        {
            "filename": "Into the Wild.mp4",
            "size": 892307874
        },
        {
            "filename": "Into the Wild.srt",
            "size": 86679
        },
        {
            "filename": "IP Man.mp4",
            "size": 680918615
        },
        {
            "filename": "IP Man.srt",
            "size": 65461
        },
        {
            "filename": "IP Man 2.mp4",
            "size": 681339598
        },
        {
            "filename": "IP Man 2.srt",
            "size": 52899
        },
        {
            "filename": "It Chapter Two.mp4",
            "size": 1585121071
        },
        {
            "filename": "It Chapter Two.srt",
            "size": 159529
        },
        {
            "filename": "Cover.jpg",
            "size": 208683
        },
        {
            "filename": "Jack Reacher.mp4",
            "size": 1184206416
        },
        {
            "filename": "Jack Reacher.srt",
            "size": 107048
        },
        {
            "filename": "Jack Reacher- Never Go Back.mp4",
            "size": 915600683
        },
        {
            "filename": "Jack Reacher- Never Go Back.srt",
            "size": 98432
        },
        {
            "filename": "JFK.mkv",
            "size": 943889755
        },
        {
            "filename": "JFK.srt",
            "size": 296314
        },
        {
            "filename": "Joint Security Area.mkv",
            "size": 789739742
        },
        {
            "filename": "Joint Security Area.srt",
            "size": 50183
        },
        {
            "filename": "Jojo Rabbit.mp4",
            "size": 1044810985
        },
        {
            "filename": "Jojo Rabbit.srt",
            "size": 125660
        },
        {
            "filename": "Juno.mkv",
            "size": 524501642
        },
        {
            "filename": "Jurassic Park.mp4",
            "size": 793302687
        },
        {
            "filename": "Jurassic Park.srt",
            "size": 91120
        },
        {
            "filename": "Jurassic World.mkv",
            "size": 1211597294
        },
        {
            "filename": "K-PAX.mkv",
            "size": 682728859
        },
        {
            "filename": "K.G.F- Chapter 1.mp4",
            "size": 1492612111
        },
        {
            "filename": "Knives Out.mp4",
            "size": 1253682826
        },
        {
            "filename": "Knives Out.srt",
            "size": 198816
        },
        {
            "filename": "Kubo And The Two Strings.mp4",
            "size": 788536179
        },
        {
            "filename": "Kubo And The Two Strings.srt",
            "size": 82249
        },
        {
            "filename": "L.A. Confidential.mkv",
            "size": 628495437
        },
        {
            "filename": "Lady Bird.mp4",
            "size": 905163736
        },
        {
            "filename": "Lady Bird.srt",
            "size": 120794
        },
        {
            "filename": "Les Mis\u00e9rables (2019).mp4",
            "size": 1002589847
        },
        {
            "filename": "Les Mis\u00e9rables (2019).srt",
            "size": 81879
        },
        {
            "filename": "Life of Pi.mp4",
            "size": 1076756260
        },
        {
            "filename": "Life of Pi.srt",
            "size": 73056
        },
        {
            "filename": "Limitless.mp4",
            "size": 787485130
        },
        {
            "filename": "Limitless.srt",
            "size": 95922
        },
        {
            "filename": "Little Manhattan.mp4",
            "size": 867228183
        },
        {
            "filename": "Little Manhattan.srt",
            "size": 121470
        },
        {
            "filename": "Little Women.mp4",
            "size": 1300333989
        },
        {
            "filename": "Little Women.srt",
            "size": 141020
        },
        {
            "filename": "Lone Survivor.mp4",
            "size": 909719244
        },
        {
            "filename": "Lone Survivor.srt",
            "size": 78168
        },
        {
            "filename": "Looper.mp4",
            "size": 839653241
        },
        {
            "filename": "Looper.srt",
            "size": 66428
        },
        {
            "filename": "Lost in Translation.mkv",
            "size": 929983625
        },
        {
            "filename": "Lost in Translation.srt",
            "size": 73101
        },
        {
            "filename": "Lucky Number Slevin.mp4",
            "size": 786344353
        },
        {
            "filename": "Lucky Number Slevin.srt",
            "size": 113898
        },
        {
            "filename": "Madagascar 3- Europe's Most Wanted.mkv",
            "size": 822032892
        },
        {
            "filename": "Madagascar 3- Europe's Most Wanted.srt",
            "size": 118669
        },
        {
            "filename": "Man of Steel.mp4",
            "size": 1026441629
        },
        {
            "filename": "Man of Steel.srt",
            "size": 117066
        },
        {
            "filename": "Manchester By The Sea.mp4",
            "size": 1048541843
        },
        {
            "filename": "Manchester By The Sea.srt",
            "size": 131894
        },
        {
            "filename": "Marriage Story.mp4",
            "size": 1318962454
        },
        {
            "filename": "Marriage Story.srt",
            "size": 214203
        },
        {
            "filename": "McFarland, USA.mp4",
            "size": 913709781
        },
        {
            "filename": "McFarland, USA.srt",
            "size": 130902
        },
        {
            "filename": "Me and Earl and the Dying Girl.mp4",
            "size": 827823361
        },
        {
            "filename": "Me and Earl and the Dying Girl.srt",
            "size": 135241
        },
        {
            "filename": "Memento.mkv",
            "size": 629091074
        },
        {
            "filename": "Memories Of Murder.mp4",
            "size": 1264915462
        },
        {
            "filename": "Memories Of Murder.srt",
            "size": 93556
        },
        {
            "filename": "Men in Black 3.mkv",
            "size": 887371027
        },
        {
            "filename": "Men in Black II.mkv",
            "size": 709988652
        },
        {
            "filename": "Cover.jpg",
            "size": 437959
        },
        {
            "filename": "Men, Women & Children.mkv",
            "size": 943114107
        },
        {
            "filename": "Million Dollar Baby.mp4",
            "size": 800790627
        },
        {
            "filename": "Million Dollar Baby.srt",
            "size": 89819
        },
        {
            "filename": "Miracle In Cell No. 7.mp4",
            "size": 1230366860
        },
        {
            "filename": "Miracle in Cell No. 7.srt",
            "size": 98369
        },
        {
            "filename": "Mirage.mp4",
            "size": 1241188384
        },
        {
            "filename": "Mirage.srt",
            "size": 90497
        },
        {
            "filename": "Mission Impossible- Ghost Protocol.mp4",
            "size": 891748686
        },
        {
            "filename": "Mission Impossible- Ghost Protocol.srt",
            "size": 79246
        },
        {
            "filename": "Mission Impossible- Rogue Nation.mp4",
            "size": 1034610625
        },
        {
            "filename": "Mission Impossible- Rogue Nation.srt",
            "size": 106347
        },
        {
            "filename": "Mission Impossible- Fallout.mp4",
            "size": 2551930711
        },
        {
            "filename": "Mission Impossible- Fallout.srt",
            "size": 112058
        },
        {
            "filename": "Modern Family S04 E13.mkv",
            "size": 211206715
        },
        {
            "filename": "Modern Family S04 E13.srt",
            "size": 40771
        },
        {
            "filename": "Cover.jpg",
            "size": 95598
        },
        {
            "filename": "Moneyball.mp4",
            "size": 850299322
        },
        {
            "filename": "Moneyball.srt",
            "size": 148521
        },
        {
            "filename": "Cover.jpg",
            "size": 307685
        },
        {
            "filename": "Monsters University.mp4",
            "size": 849638125
        },
        {
            "filename": "Monsters University.srt",
            "size": 98074
        },
        {
            "filename": "Monsters, Inc..mkv",
            "size": 717144235
        },
        {
            "filename": "Montage.mp4",
            "size": 1109996804
        },
        {
            "filename": "Montage.srt",
            "size": 86406
        },
        {
            "filename": "Mr. Church.mp4",
            "size": 865561249
        },
        {
            "filename": "Mr. Church.srt",
            "size": 111045
        },
        {
            "filename": "My Life As A Zucchini.mp4",
            "size": 582370866
        },
        {
            "filename": "My Life As A Zucchini.srt",
            "size": 46857
        },
        {
            "filename": "Mystic River.mkv",
            "size": 686555765
        },
        {
            "filename": "Cover.jpg",
            "size": 626857
        },
        {
            "filename": "Nightcrawler.mp4",
            "size": 906901867
        },
        {
            "filename": "Nightcrawler.srt",
            "size": 156980
        },
        {
            "filename": "No Country for Old Men.mp4",
            "size": 788833720
        },
        {
            "filename": "No Country for Old Men.srt",
            "size": 71687
        },
        {
            "filename": "Nocturnal Animals.mp4",
            "size": 888725935
        },
        {
            "filename": "Nocturnal Animals.srt",
            "size": 105898
        },
        {
            "filename": "Oblivion.mp4",
            "size": 680499320
        },
        {
            "filename": "Oblivion.srt",
            "size": 98023
        },
        {
            "filename": "Ocean's Thirteen.mkv",
            "size": 847386386
        },
        {
            "filename": "Ocean's Twelve.mkv",
            "size": 800637318
        },
        {
            "filename": "Oldboy.mp4",
            "size": 1061799749
        },
        {
            "filename": "Oldboy.srt",
            "size": 69457
        },
        {
            "filename": "Once.mp4",
            "size": 734884127
        },
        {
            "filename": "Once.srt",
            "size": 72854
        },
        {
            "filename": "Once Upon A Time ... In Hollywood.mp4",
            "size": 1499127548
        },
        {
            "filename": "Once Upon A Time ... In Hollywood.srt",
            "size": 141810
        },
        {
            "filename": "Paddington.mp4",
            "size": 753910269
        },
        {
            "filename": "Paddington.srt",
            "size": 109124
        },
        {
            "filename": "Panic Room.mkv",
            "size": 583881852
        },
        {
            "filename": "Panic Room.srt",
            "size": 68803
        },
        {
            "filename": "Patriots Day.mp4",
            "size": 1013875769
        },
        {
            "filename": "Patriots Day.srt",
            "size": 147282
        },
        {
            "filename": "Peaceful Warrior.mp4",
            "size": 1074994098
        },
        {
            "filename": "Peaceful Warrior.srt",
            "size": 73237
        },
        {
            "filename": "Percy Jackson & the Olympians- The Lightning Thief.mp4",
            "size": 787333998
        },
        {
            "filename": "Percy Jackson & the Olympians- The Lightning Thief.srt",
            "size": 87116
        },
        {
            "filename": "Planes, Trains & Automobiles.mkv",
            "size": 636143224
        },
        {
            "filename": "Planes, Trains & Automobiles.srt",
            "size": 79990
        },
        {
            "filename": "Cover.jpg",
            "size": 525317
        },
        {
            "filename": "Prince of Persia- The Sands of Time.mkv",
            "size": 896493651
        },
        {
            "filename": "Prince of Persia- The Sands of Time.srt",
            "size": 85191
        },
        {
            "filename": "Prometheus.mp4",
            "size": 839860428
        },
        {
            "filename": "Prometheus.srt",
            "size": 93739
        },
        {
            "filename": "Pulp Fiction.mp4",
            "size": 622250788
        },
        {
            "filename": "Pulp Fiction.srt",
            "size": 170248
        },
        {
            "filename": "Rang De Basanti.mp4",
            "size": 1604097080
        },
        {
            "filename": "Raya And The Last Dragon.mp4",
            "size": 2127333394
        },
        {
            "filename": "Raya And The Last Dragon.srt",
            "size": 119313
        },
        {
            "filename": "Real Steel.mp4",
            "size": 667549397
        },
        {
            "filename": "Real Steel.srt",
            "size": 115330
        },
        {
            "filename": "Requiem for a Dream.mp4",
            "size": 734157820
        },
        {
            "filename": "Requiem for a Dream.srt",
            "size": 82691
        },
        {
            "filename": "Reservoir Dogs.mp4",
            "size": 670250196
        },
        {
            "filename": "Reservoir Dogs.srt",
            "size": 135805
        },
        {
            "filename": "Richard Jewell.mp4",
            "size": 1261689533
        },
        {
            "filename": "Richard Jewell.srt",
            "size": 191707
        },
        {
            "filename": "Ride Along.mp4",
            "size": 794436659
        },
        {
            "filename": "Ride Along.srt",
            "size": 173442
        },
        {
            "filename": "Rio.mkv",
            "size": 733545918
        },
        {
            "filename": "Rise of the Guardians.mkv",
            "size": 894955310
        },
        {
            "filename": "Rise of the Guardians.srt",
            "size": 82672
        },
        {
            "filename": "Rise of the Planet of the Apes.mkv",
            "size": 873579013
        },
        {
            "filename": "Rise of the Planet of the Apes.srt",
            "size": 54538
        },
        {
            "filename": "Road to Perdition.mp4",
            "size": 787568098
        },
        {
            "filename": "Road to Perdition.srt",
            "size": 52583
        },
        {
            "filename": "Rocky.mp4",
            "size": 788414150
        },
        {
            "filename": "Rocky.srt",
            "size": 136431
        },
        {
            "filename": "Rocky II.mp4",
            "size": 788324810
        },
        {
            "filename": "Rocky II.srt",
            "size": 128960
        },
        {
            "filename": "Cover.jpg",
            "size": 461817
        },
        {
            "filename": "Room.mp4",
            "size": 925207070
        },
        {
            "filename": "Room.srt",
            "size": 114077
        },
        {
            "filename": "Rush.mp4",
            "size": 913581666
        },
        {
            "filename": "Rush.srt",
            "size": 124839
        },
        {
            "filename": "Sarkar.mkv",
            "size": 815345374
        },
        {
            "filename": "Satan's Slaves.mp4",
            "size": 947867580
        },
        {
            "filename": "Satan's Slaves.srt",
            "size": 50157
        },
        {
            "filename": "Saw.mp4",
            "size": 629126417
        },
        {
            "filename": "Saw.srt",
            "size": 66889
        },
        {
            "filename": "Saw II.mp4",
            "size": 628567344
        },
        {
            "filename": "Saw II.srt",
            "size": 77478
        },
        {
            "filename": "Saw III.mp4",
            "size": 681475871
        },
        {
            "filename": "Saw III.srt",
            "size": 67230
        },
        {
            "filename": "Cover.jpg",
            "size": 430944
        },
        {
            "filename": "Schindler's List.mp4",
            "size": 1286872149
        },
        {
            "filename": "Schindler's List.srt",
            "size": 178048
        },
        {
            "filename": "Searching.mp4",
            "size": 911813949
        },
        {
            "filename": "Searching.srt",
            "size": 87274
        },
        {
            "filename": "Shang-Chi And The Legend Of The Ten Rings.mp4",
            "size": 2619721036
        },
        {
            "filename": "Shang-Chi And The Legend Of The Ten Rings.srt",
            "size": 126178
        },
        {
            "filename": "Cover.jpg",
            "size": 80854
        },
        {
            "filename": "Sherlock Holmes.mkv",
            "size": 813391127
        },
        {
            "filename": "Sherlock Holmes.srt",
            "size": 114623
        },
        {
            "filename": "Cover.jpg",
            "size": 119520
        },
        {
            "filename": "Sherlock Holmes- A Game Of Shadows.mp4",
            "size": 841467769
        },
        {
            "filename": "Sherlock Holmes- A Game of Shadows.srt",
            "size": 91241
        },
        {
            "filename": "Short Term 12.mp4",
            "size": 794529379
        },
        {
            "filename": "Short Term 12.srt",
            "size": 80245
        },
        {
            "filename": "Sicario.mp4",
            "size": 912462650
        },
        {
            "filename": "Sicario.srt",
            "size": 102708
        },
        {
            "filename": "Sicario- Day of The Soldado.mkv",
            "size": 1194097367
        },
        {
            "filename": "Sinister.mkv",
            "size": 758447718
        },
        {
            "filename": "Skyfall.mkv",
            "size": 1131986740
        },
        {
            "filename": "Skyfall.srt",
            "size": 92373
        },
        {
            "filename": "Slumdog Millionaire.mp4",
            "size": 732797568
        },
        {
            "filename": "Slumdog Millionaire.srt",
            "size": 68093
        },
        {
            "filename": "Cover.jpg",
            "size": 284547
        },
        {
            "filename": "Soul.mp4",
            "size": 1989995242
        },
        {
            "filename": "Soul.srt",
            "size": 126076
        },
        {
            "filename": "Sound Of Metal.mp4",
            "size": 2388202877
        },
        {
            "filename": "Sound Of Metal.srt",
            "size": 80102
        },
        {
            "filename": "Spectre.mp4",
            "size": 1165160097
        },
        {
            "filename": "Spider-Man No Way Home (2021).mp4",
            "size": 2933066258
        },
        {
            "filename": "Spider-Man No Way Home (2021).srt",
            "size": 159305
        },
        {
            "filename": "SpiderMan 2.mp4",
            "size": 732870071
        },
        {
            "filename": "SpiderMan 2.srt",
            "size": 76957
        },
        {
            "filename": "Spotlight.mp4",
            "size": 988058000
        },
        {
            "filename": "Spotlight.srt",
            "size": 180774
        },
        {
            "filename": "Spring.mp4",
            "size": 853234365
        },
        {
            "filename": "Spring.srt",
            "size": 118519
        },
        {
            "filename": "Spring, Summer, Fall, Winter... And Spring.mp4",
            "size": 1013080763
        },
        {
            "filename": "Spring, Summer, Fall, Winter... And Spring.srt",
            "size": 8443
        },
        {
            "filename": "Star Trek.mp4",
            "size": 787926398
        },
        {
            "filename": "Star Trek.srt",
            "size": 110304
        },
        {
            "filename": "Star Trek Into Darkness.mp4",
            "size": 967620072
        },
        {
            "filename": "Sunshine.mp4",
            "size": 735427077
        },
        {
            "filename": "Sunshine.srt",
            "size": 67484
        },
        {
            "filename": "Take Shelter.mp4",
            "size": 788275152
        },
        {
            "filename": "Take Shelter.srt",
            "size": 81521
        },
        {
            "filename": "Talvar.mkv",
            "size": 1099015160
        },
        {
            "filename": "Tangerines.mkv",
            "size": 789319609
        },
        {
            "filename": "Tanu Weds Manu.mp4",
            "size": 932120101
        },
        {
            "filename": "Tanu Weds Manu Returns.mp4",
            "size": 999596189
        },
        {
            "filename": "Tenet.mp4",
            "size": 2973650753
        },
        {
            "filename": "Tenet.srt",
            "size": 131329
        },
        {
            "filename": "The Accountant.mp4",
            "size": 989842501
        },
        {
            "filename": "The Accountant.srt",
            "size": 109164
        },
        {
            "filename": "Cover.jpg",
            "size": 156495
        },
        {
            "filename": "The Adjustment Bureau.mkv",
            "size": 680753896
        },
        {
            "filename": "The Best Exotic Marigold Hotel.mp4",
            "size": 785694708
        },
        {
            "filename": "The Best Exotic Marigold Hotel.srt",
            "size": 135226
        },
        {
            "filename": "The Blind Side.mkv",
            "size": 628564023
        },
        {
            "filename": "The Body.mp4",
            "size": 1081187029
        },
        {
            "filename": "The Body.srt",
            "size": 130261
        },
        {
            "filename": "The Bourne Identity.mkv",
            "size": 691088650
        },
        {
            "filename": "The Bourne Identity.srt",
            "size": 86381
        },
        {
            "filename": "The Bourne Supremacy.mkv",
            "size": 629365965
        },
        {
            "filename": "The Bourne Supremacy.srt",
            "size": 51475
        },
        {
            "filename": "The Bourne Ultimatum.mkv",
            "size": 688642636
        },
        {
            "filename": "The Bourne Ultimatum.srt",
            "size": 70140
        },
        {
            "filename": "The Boy Who Harnessed the Wind.mp4",
            "size": 1019754112
        },
        {
            "filename": "The Boy Who Harnessed the Wind.srt",
            "size": 61914
        },
        {
            "filename": "The Call.mp4",
            "size": 789182244
        },
        {
            "filename": "The Call.srt",
            "size": 98412
        },
        {
            "filename": "The Chaser.mkv",
            "size": 944063810
        },
        {
            "filename": "The Chaser.srt",
            "size": 85457
        },
        {
            "filename": "._Batman.The.Dark.Knight.2008.1080p.BluRay.x264.YIFY.mp4",
            "size": 4096
        },
        {
            "filename": "The Dark Knight.mp4",
            "size": 1828285704
        },
        {
            "filename": "The Dark Knight.srt",
            "size": 142609
        },
        {
            "filename": "The Dark Knight Rises.mp4",
            "size": 2662526944
        },
        {
            "filename": "The Dark Knight Rises.srt",
            "size": 148057
        },
        {
            "filename": "The Fast and the Furious.mkv",
            "size": 625510327
        },
        {
            "filename": "The Fast and the Furious.srt",
            "size": 64121
        },
        {
            "filename": "The Fate Of The Furious.mp4",
            "size": 1056213133
        },
        {
            "filename": "The Fate Of The Furious.srt",
            "size": 108645
        },
        {
            "filename": "Cover.jpg",
            "size": 163817
        },
        {
            "filename": "The Fault in Our Stars.mp4",
            "size": 922298155
        },
        {
            "filename": "The Fault in Our Stars.srt",
            "size": 141024
        },
        {
            "filename": "The Florida Project.mp4",
            "size": 842924428
        },
        {
            "filename": "The Florida Project.srt",
            "size": 132653
        },
        {
            "filename": "The Gangster, The Cop, The Devil.mp4",
            "size": 1027265005
        },
        {
            "filename": "The Gangster, The Cop, The Devil.srt",
            "size": 94348
        },
        {
            "filename": "The Gentlemen.mp4",
            "size": 1094180689
        },
        {
            "filename": "The Gentlemen.srt",
            "size": 154953
        },
        {
            "filename": "The Grand Budapest Hotel.mp4",
            "size": 796710310
        },
        {
            "filename": "The Grand Budapest Hotel.srt",
            "size": 109654
        },
        {
            "filename": "The Green Mile.mp4",
            "size": 1339251886
        },
        {
            "filename": "The Green Mile.srt",
            "size": 141028
        },
        {
            "filename": "The Hangover.mp4",
            "size": 848708306
        },
        {
            "filename": "The Hangover.srt",
            "size": 143120
        },
        {
            "filename": "The Help.mp4",
            "size": 892880947
        },
        {
            "filename": "The Help.srt",
            "size": 143888
        },
        {
            "filename": "The Hobbit- An Unexpected Journey.mkv",
            "size": 1307999083
        },
        {
            "filename": "The Hobbit- The Battle of the Five Armies.mp4",
            "size": 979422887
        },
        {
            "filename": "The Hobbit- The Battle of the Five Armies.srt",
            "size": 97879
        },
        {
            "filename": "The Hobbit- The Desolation of Smaug.mp4",
            "size": 1041403545
        },
        {
            "filename": "The Hobbit- The Desolation of Smaug.srt",
            "size": 105254
        },
        {
            "filename": "The Hours.mkv",
            "size": 618027012
        },
        {
            "filename": "The Hunt.mp4",
            "size": 991010166
        },
        {
            "filename": "The Hunt.srt",
            "size": 61755
        },
        {
            "filename": "The Hurt Locker.mp4",
            "size": 838971754
        },
        {
            "filename": "The Hurt Locker.srt",
            "size": 100326
        },
        {
            "filename": "The Imitation Game.mp4",
            "size": 853275583
        },
        {
            "filename": "The Imitation Game.srt",
            "size": 120912
        },
        {
            "filename": "The Incredibles.mp4",
            "size": 735208247
        },
        {
            "filename": "The Incredibles.srt",
            "size": 104472
        },
        {
            "filename": "The Intouchables.mp4",
            "size": 733736213
        },
        {
            "filename": "The Intouchables.srt",
            "size": 105569
        },
        {
            "filename": "The Invisible Guest.mp4",
            "size": 963151526
        },
        {
            "filename": "The Invisible Guest.srt",
            "size": 92764
        },
        {
            "filename": "The Irishman.mp4",
            "size": 2013318250
        },
        {
            "filename": "The Irishman.srt",
            "size": 241549
        },
        {
            "filename": "The Last Samurai.mp4",
            "size": 1077155701
        },
        {
            "filename": "The Last Samurai.srt",
            "size": 69762
        },
        {
            "filename": "The Lion King.mkv",
            "size": 566286606
        },
        {
            "filename": "The Lord of the Rings- The Fellowship of the Ring.mp4",
            "size": 1509349967
        },
        {
            "filename": "The Lord of the Rings- The Fellowship of the Ring.srt",
            "size": 155679
        },
        {
            "filename": "The Lord of the Rings- The Fellowship of the Ringd.srt",
            "size": 99147
        },
        {
            "filename": "The Lord of the Rings- The Return of the King.mp4",
            "size": 1827743197
        },
        {
            "filename": "The Lord of the Rings- The Return of the King.srt",
            "size": 122650
        },
        {
            "filename": "The Lord of the Rings- The Two Towers.mp4",
            "size": 1613605816
        },
        {
            "filename": "The Lord of the Rings- The Two Towers.srt",
            "size": 136219
        },
        {
            "filename": "Cover.jpg",
            "size": 294782
        },
        {
            "filename": "The Lunchbox.mkv",
            "size": 787023350
        },
        {
            "filename": "The Matrix Reloaded.mkv",
            "size": 805273984
        },
        {
            "filename": "The Matrix Revolutions.mkv",
            "size": 737538549
        },
        {
            "filename": "The Maze Runner.mp4",
            "size": 853995707
        },
        {
            "filename": "The Maze Runner.srt",
            "size": 99146
        },
        {
            "filename": "The Next Three Days.mp4",
            "size": 788532448
        },
        {
            "filename": "The Next Three Days.srt",
            "size": 71833
        },
        {
            "filename": "The Night Comes for Us.mkv",
            "size": 995098624
        },
        {
            "filename": "The Night Comes for Us.srt",
            "size": 31354
        },
        {
            "filename": "Cover.jpg",
            "size": 535168
        },
        {
            "filename": "The Perks of Being a Wallflower.mkv",
            "size": 732755415
        },
        {
            "filename": "The Pianist.mkv",
            "size": 942895807
        },
        {
            "filename": "The Platform.mkv",
            "size": 787610177
        },
        {
            "filename": "The Pursuit of Happyness.mp4",
            "size": 734419597
        },
        {
            "filename": "The Pursuit of Happyness.srt",
            "size": 106528
        },
        {
            "filename": "The Revenant.mkv",
            "size": 1506185859
        },
        {
            "filename": "The Road to El Dorado.mp4",
            "size": 805082756
        },
        {
            "filename": "The Road to El Dorado.srt",
            "size": 108243
        },
        {
            "filename": "The Shawshank Redemption.mp4",
            "size": 890203389
        },
        {
            "filename": "The Shawshank Redemption.srt",
            "size": 139131
        },
        {
            "filename": "The Shining.mkv",
            "size": 681584145
        },
        {
            "filename": "The Silence of the Lambs.mp4",
            "size": 788356788
        },
        {
            "filename": "The Silence of the Lambs.srt",
            "size": 95249
        },
        {
            "filename": "The Sixth Sense.mkv",
            "size": 732913782
        },
        {
            "filename": "Cover.jpg",
            "size": 410322
        },
        {
            "filename": "The Social Network.mp4",
            "size": 733355753
        },
        {
            "filename": "The Social Network.srt",
            "size": 185577
        },
        {
            "filename": "Cover.jpg",
            "size": 496336
        },
        {
            "filename": "The Spectacular Now.mp4",
            "size": 723082525
        },
        {
            "filename": "The Spectacular Now.srt",
            "size": 120376
        },
        {
            "filename": "The Terminal.mkv",
            "size": 848336234
        },
        {
            "filename": "The Terminal.srt",
            "size": 105451
        },
        {
            "filename": "The Terminator.mkv",
            "size": 622814097
        },
        {
            "filename": "The Trial of Chicago 7.mp4",
            "size": 1252039306
        },
        {
            "filename": "The Trial of Chicago 7.srt",
            "size": 180529
        },
        {
            "filename": "The Trial of Chicago 71.srt",
            "size": 305102
        },
        {
            "filename": "[BLUE] The Trial of the Chicago 7.2020.NF.1080p.WEB-DL.H264.DDP5.1-EVO.srt",
            "size": 305102
        },
        {
            "filename": "[GREEN] The Trial of the Chicago 7.2020.NF.1080p.WEB-DL.H264.DDP5.1-EVO.srt",
            "size": 305102
        },
        {
            "filename": "The Truman Show.mkv",
            "size": 577791371
        },
        {
            "filename": "Twilight Saga - Eclipse.mp4",
            "size": 735025857
        },
        {
            "filename": "Twilight Saga - Eclipse.srt",
            "size": 92300
        },
        {
            "filename": "The Twilight Saga- Breaking Dawn Part 1.mp4",
            "size": 788415125
        },
        {
            "filename": "The Twilight Saga- Breaking Dawn Part 1.srt",
            "size": 78965
        },
        {
            "filename": "Cover.jpg",
            "size": 169688
        },
        {
            "filename": "The Twilight Saga- Breaking Dawn Part 2.mkv",
            "size": 810393836
        },
        {
            "filename": "The Twilight Saga- New Moon.mp4",
            "size": 736343937
        },
        {
            "filename": "The Twilight Saga- New Moon.srt",
            "size": 99885
        },
        {
            "filename": "The Usual Suspects.mkv",
            "size": 523912094
        },
        {
            "filename": "The Village.mp4",
            "size": 971249535
        },
        {
            "filename": "The Village.srt",
            "size": 56331
        },
        {
            "filename": "The Wailing.mp4",
            "size": 1503921645
        },
        {
            "filename": "The Wailing.srt",
            "size": 75711
        },
        {
            "filename": "Cover.jpg",
            "size": 945621
        },
        {
            "filename": "The Walk.mp4",
            "size": 1988957091
        },
        {
            "filename": "The Walk.srt",
            "size": 114800
        },
        {
            "filename": "Cover.jpg",
            "size": 392610
        },
        {
            "filename": "The Wolf of Wall Street.mp4",
            "size": 1058005877
        },
        {
            "filename": "The Wolf of Wall Street.srt",
            "size": 307545
        },
        {
            "filename": "The Wolverine.mp4",
            "size": 1024444906
        },
        {
            "filename": "The Wolverine.srt",
            "size": 72500
        },
        {
            "filename": "The Yellow Sea.mkv",
            "size": 996233342
        },
        {
            "filename": "The Yellow Sea.srt",
            "size": 62175
        },
        {
            "filename": "Toy Story.mp4",
            "size": 525927805
        },
        {
            "filename": "Toy Story.srt",
            "size": 87407
        },
        {
            "filename": "Toy Story 2.mkv",
            "size": 615995438
        },
        {
            "filename": "Toy Story 3.mp4",
            "size": 1500785177
        },
        {
            "filename": "Toy Story 3.srt",
            "size": 90731
        },
        {
            "filename": "Cover.jpg",
            "size": 324053
        },
        {
            "filename": "Traffic.mp4",
            "size": 1037246333
        },
        {
            "filename": "Traffic.srt",
            "size": 112952
        },
        {
            "filename": "Training Day.mp4",
            "size": 838165995
        },
        {
            "filename": "Training Day.srt",
            "size": 153075
        },
        {
            "filename": "Transformers- Age of Extinction.mp4",
            "size": 2428767917
        },
        {
            "filename": "Transformers- Age of Extinction.srt",
            "size": 180242
        },
        {
            "filename": "Troy.mkv",
            "size": 1062430021
        },
        {
            "filename": "Truman.mp4",
            "size": 764733566
        },
        {
            "filename": "Truman.srt",
            "size": 91767
        },
        {
            "filename": "Twilight.mp4",
            "size": 733876070
        },
        {
            "filename": "Twilight.srt",
            "size": 117494
        },
        {
            "filename": "Unbreakable.mkv",
            "size": 660326988
        },
        {
            "filename": "Unfriended.mp4",
            "size": 679282653
        },
        {
            "filename": "Unfriended.srt",
            "size": 89971
        },
        {
            "filename": "Up.mp4",
            "size": 1540666427
        },
        {
            "filename": "Upstream Color.mkv",
            "size": 680528838
        },
        {
            "filename": "V for Vendetta.mkv",
            "size": 733041176
        },
        {
            "filename": "V for Vendetta.srt",
            "size": 145771
        },
        {
            "filename": "Wall-E.mp4",
            "size": 1293552945
        },
        {
            "filename": "Wall-E.srt",
            "size": 52183
        },
        {
            "filename": "Wanted.mkv",
            "size": 773775067
        },
        {
            "filename": "Wanted.srt",
            "size": 59594
        },
        {
            "filename": "War for The Planet of The Apes.mp4",
            "size": 1098907095
        },
        {
            "filename": "Watchmen.mp4",
            "size": 1078973614
        },
        {
            "filename": "Watchmen.srt",
            "size": 150775
        },
        {
            "filename": "Widows.mp4",
            "size": 1161484356
        },
        {
            "filename": "Widows.srt",
            "size": 129421
        },
        {
            "filename": "Wild.mp4",
            "size": 856698314
        },
        {
            "filename": "Wild.srt",
            "size": 90230
        },
        {
            "filename": "Cover.jpg",
            "size": 611376
        },
        {
            "filename": "Wild Tales.mp4",
            "size": 901030822
        },
        {
            "filename": "Wild Tales.srt",
            "size": 83208
        },
        {
            "filename": "Wind River.mp4",
            "size": 820833534
        },
        {
            "filename": "Wind River.srt",
            "size": 101426
        },
        {
            "filename": "Cover.jpg",
            "size": 241709
        },
        {
            "filename": "X-Men Apocalypse.mp4",
            "size": 2362991508
        },
        {
            "filename": "X-Men Apocalypse.srt",
            "size": 98184
        },
        {
            "filename": "Cover.jpg",
            "size": 419843
        },
        {
            "filename": "desktop.ini",
            "size": 91
        },
        {
            "filename": "X-Men Days of Future Past.mp4",
            "size": 2098078128
        },
        {
            "filename": "X-Men Days of Future Past.srt",
            "size": 91563
        },
        {
            "filename": "Cover.jpg",
            "size": 345230
        },
        {
            "filename": "X-Men First Class.mp4",
            "size": 840839512
        },
        {
            "filename": "X-Men First Class.srt",
            "size": 102950
        },
        {
            "filename": "X-Men Origins- Wolverine.mkv",
            "size": 745923760
        },
        {
            "filename": "X-Men Origins- Wolverine.srt",
            "size": 81082
        },
        {
            "filename": "X-Men The Last Stand.mp4",
            "size": 683026453
        },
        {
            "filename": "X-Men The Last Stand.srt",
            "size": 57474
        },
        {
            "filename": "X-Men United (X2).mkv",
            "size": 756980961
        },
        {
            "filename": "X-Men United (X2).srt",
            "size": 98881
        },
        {
            "filename": "You Were Never Really Here.mp4",
            "size": 795064942
        },
        {
            "filename": "You Were Never Really Here.srt",
            "size": 34086
        },
        {
            "filename": "Cover.jpg",
            "size": 102887
        },
        {
            "filename": "Your Name.mkv",
            "size": 783996919
        },
        {
            "filename": "Cover.jpg",
            "size": 162484
        },
        {
            "filename": "Zero Dark Thirty.mp4",
            "size": 1074343734
        },
        {
            "filename": "Zero Dark Thirty.srt",
            "size": 127177
        },
        {
            "filename": "Cover.jpg",
            "size": 200208
        },
        {
            "filename": "Zodiac.mkv",
            "size": 727886842
        },
        {
            "filename": "Zombieland.mkv",
            "size": 635453181
        },
        {
            "filename": "Zombieland.srt",
            "size": 67337
        },
        {
            "filename": "Zombieland- Double Tap.mp4",
            "size": 923586277
        },
        {
            "filename": "Zombieland- Double Tap.srt",
            "size": 135320
        },
        {
            "filename": "Zombieland- three",
            "size": 135321
        },
    ]
}
